CHANGES.txt
LICENSE.txt
MANIFEST.in
README.txt
setup.py
ytsub/__init__.py
ytsub/api.py
ytsub/argparse_util.py
ytsub/batch.py
ytsub/credentials.py
ytsub/main.py
ytsub/video.py
ytsub.egg-info/PKG-INFO
ytsub.egg-info/SOURCES.txt
ytsub.egg-info/dependency_links.txt
ytsub.egg-info/entry_points.txt
ytsub.egg-info/requires.txt
ytsub.egg-info/top_level.txt
ytsub/data/client_secrets.json