Metadata-Version: 1.0
Name: ytsub
Version: 1.2.1
Summary: List your Youtube subscription videos
Home-page: https://github.com/jwill392/ytsub
Author: Jackson Williams
Author-email: jackson.r.williams+ytsub@gmail.com
License: LICENSE.txt
Platform: UNKNOWN
